liteui/__about__.py
liteui/__init__.py
liteui-0.0.1.dist-info/METADATA
liteui-0.0.1.dist-info/WHEEL
liteui-0.0.1.dist-info/licenses/LICENSE.txt
liteui-0.0.1.dist-info/RECORD
