Metadata-Version: 2.3
Name: LiteUI
Version: 0.0.1
Summary: LiteUI is a simple and lightweight UI library for Python.
Project-URL: Documentation, https://github.com/hasansezertasan/LiteUI#readme
Project-URL: Issues, https://github.com/hasansezertasan/LiteUI/issues
Project-URL: Source, https://github.com/hasansezertasan/LiteUI
Author-email: Hasan Sezer Taşan <hasansezertasan@gmail.com>
License-Expression: MIT
License-File: LICENSE.txt
Classifier: Development Status :: 1 - Planning
Classifier: Programming Language :: Python
Classifier: Programming Language :: Python :: 3.8
Classifier: Programming Language :: Python :: 3.9
Classifier: Programming Language :: Python :: 3.10
Classifier: Programming Language :: Python :: 3.11
Classifier: Programming Language :: Python :: 3.12
Classifier: Programming Language :: Python :: Implementation :: CPython
Classifier: Programming Language :: Python :: Implementation :: PyPy
Requires-Python: >=3.8
